modoboa_webmail/__init__.py
modoboa_webmail/apps.py
modoboa_webmail/constants.py
modoboa_webmail/exceptions.py
modoboa_webmail/forms.py
modoboa_webmail/handlers.py
modoboa_webmail/modo_extension.py
modoboa_webmail/urls.py
modoboa_webmail/validators.py
modoboa_webmail/views.py
modoboa_webmail/lib/__init__.py
modoboa_webmail/lib/attachments.py
modoboa_webmail/lib/fetch_parser.py
modoboa_webmail/lib/imapemail.py
modoboa_webmail/lib/imapheader.py
modoboa_webmail/lib/imaputils.py
modoboa_webmail/lib/rfc6266.py
modoboa_webmail/lib/sendmail.py
modoboa_webmail/lib/signature.py
modoboa_webmail/lib/utils.py
modoboa_webmail/locale/cs_CZ/LC_MESSAGES/django.mo
modoboa_webmail/locale/cs_CZ/LC_MESSAGES/django.po
modoboa_webmail/locale/cs_CZ/LC_MESSAGES/djangojs.mo
modoboa_webmail/locale/cs_CZ/LC_MESSAGES/djangojs.po
modoboa_webmail/locale/de/LC_MESSAGES/django.mo
modoboa_webmail/locale/de/LC_MESSAGES/django.po
modoboa_webmail/locale/de/LC_MESSAGES/djangojs.mo
modoboa_webmail/locale/de/LC_MESSAGES/djangojs.po
modoboa_webmail/locale/el_GR/LC_MESSAGES/django.mo
modoboa_webmail/locale/el_GR/LC_MESSAGES/django.po
modoboa_webmail/locale/el_GR/LC_MESSAGES/djangojs.mo
modoboa_webmail/locale/el_GR/LC_MESSAGES/djangojs.po
modoboa_webmail/locale/en/LC_MESSAGES/django.mo
modoboa_webmail/locale/en/LC_MESSAGES/django.po
modoboa_webmail/locale/en/LC_MESSAGES/djangojs.mo
modoboa_webmail/locale/en/LC_MESSAGES/djangojs.po
modoboa_webmail/locale/es/LC_MESSAGES/django.mo
modoboa_webmail/locale/es/LC_MESSAGES/django.po
modoboa_webmail/locale/es/LC_MESSAGES/djangojs.mo
modoboa_webmail/locale/es/LC_MESSAGES/djangojs.po
modoboa_webmail/locale/fr/LC_MESSAGES/django.mo
modoboa_webmail/locale/fr/LC_MESSAGES/django.po
modoboa_webmail/locale/fr/LC_MESSAGES/djangojs.mo
modoboa_webmail/locale/fr/LC_MESSAGES/djangojs.po
modoboa_webmail/locale/it/LC_MESSAGES/django.mo
modoboa_webmail/locale/it/LC_MESSAGES/django.po
modoboa_webmail/locale/it/LC_MESSAGES/djangojs.mo
modoboa_webmail-1.9.0.dist-info/LICENSE
modoboa_webmail-1.9.0.dist-info/METADATA
modoboa_webmail-1.9.0.dist-info/WHEEL
modoboa_webmail-1.9.0.dist-info/top_level.txt
modoboa_webmail-1.9.0.dist-info/RECORD
