Metadata-Version: 2.1
Name: modoboa-webmail
Version: 1.9.0
Summary: The webmail of Modoboa
Home-page: http://modoboa.org/
Author: Antoine Nguyen
Author-email: tonio@ngyn.org
License: MIT
Keywords: email webmail
Classifier: Development Status :: 5 - Production/Stable
Classifier: Environment :: Web Environment
Classifier: Framework :: Django :: 4.2
Classifier: Intended Audience :: System Administrators
Classifier: License :: OSI Approved :: MIT License
Classifier: Operating System :: OS Independent
Classifier: Programming Language :: Python :: 3.8
Classifier: Programming Language :: Python :: 3.9
Classifier: Programming Language :: Python :: 3.10
Classifier: Programming Language :: Python :: 3.11
Classifier: Topic :: Communications :: Email
Classifier: Topic :: Internet :: WWW/HTTP
License-File: LICENSE
Requires-Dist: chardet
Requires-Dist: lxml
